{
  "per_class": {
    "Cyberstalking": {
      "precision": 0.75,
      "recall": 0.6842105263157895,
      "f1-score": 0.7155963302752294,
      "support": 57.0
    },
    "Doxing": {
      "precision": 0.7701149425287356,
      "recall": 0.8481012658227848,
      "f1-score": 0.8072289156626506,
      "support": 79.0
    },
    "Revenge Porn": {
      "precision": 0.75,
      "recall": 0.8873239436619719,
      "f1-score": 0.8129032258064516,
      "support": 71.0
    },
    "Sexual Harassment": {
      "precision": 0.918918918918919,
      "recall": 0.8292682926829268,
      "f1-score": 0.8717948717948718,
      "support": 82.0
    },
    "Slut Shaming": {
      "precision": 0.9506172839506173,
      "recall": 0.8651685393258427,
      "f1-score": 0.9058823529411765,
      "support": 89.0
    }
  },
  "weighted_avg": {
    "precision": 0.8380829896368425,
    "recall": 0.8306878306878307,
    "f1-score": 0.8317114103022215,
    "support": 378.0
  },
  "micro_avg": {
    "precision": 0.8306878306878307,
    "recall": 0.8306878306878307,
    "f1-score": 0.8306878306878307,
    "support": 378
  },
  "macro_avg": {
    "precision": 0.8279302290796544,
    "recall": 0.8228145135618631,
    "f1-score": 0.822681139296076,
    "support": 378.0
  },
  "accuracy": 0.8306878306878307,
  "inference_time_seconds": 0.2341477870941162,
  "energy_kwh": 1.2434820326188703e-05,
  "num_test_samples": 378
}