{
  "per_class": {
    "age": {
      "precision": 0.9857972885732731,
      "recall": 0.9763427109974424,
      "f1-score": 0.9810472213299068,
      "support": 1564.0
    },
    "ethnicity": {
      "precision": 0.9858490566037735,
      "recall": 0.987846049966239,
      "f1-score": 0.9868465430016864,
      "support": 1481.0
    },
    "gender": {
      "precision": 0.8981026001405481,
      "recall": 0.8771448181194235,
      "f1-score": 0.8875,
      "support": 1457.0
    },
    "not_cyberbullying": {
      "precision": 0.6473594548551959,
      "recall": 0.6244864420706656,
      "f1-score": 0.6357172731074864,
      "support": 1217.0
    },
    "other_cyberbullying": {
      "precision": 0.6130558183538316,
      "recall": 0.6605504587155964,
      "f1-score": 0.6359175662414132,
      "support": 981.0
    },
    "religion": {
      "precision": 0.956140350877193,
      "recall": 0.9639924194567278,
      "f1-score": 0.9600503302925448,
      "support": 1583.0
    }
  },
  "weighted_avg": {
    "precision": 0.8708413968810872,
    "recall": 0.869491730049499,
    "f1-score": 0.8700021503142832,
    "support": 8283.0
  },
  "micro_avg": {
    "precision": 0.869491730049499,
    "recall": 0.869491730049499,
    "f1-score": 0.869491730049499,
    "support": 8283
  },
  "macro_avg": {
    "precision": 0.8477174282339691,
    "recall": 0.8483938165543492,
    "f1-score": 0.8478464889955063,
    "support": 8283.0
  },
  "accuracy": 0.869491730049499,
  "inference_time_seconds": 6.497173070907593,
  "energy_kwh": 0.0003855082771696304,
  "num_test_samples": 8283
}