{
  "per_class": {
    "Cyberstalking": {
      "precision": 0.7540983606557377,
      "recall": 0.7666666666666667,
      "f1-score": 0.7603305785123967,
      "support": 60.0
    },
    "Doxing": {
      "precision": 0.8395061728395061,
      "recall": 0.7727272727272727,
      "f1-score": 0.8047337278106509,
      "support": 88.0
    },
    "Revenge Porn": {
      "precision": 0.7439024390243902,
      "recall": 0.8026315789473685,
      "f1-score": 0.7721518987341772,
      "support": 76.0
    },
    "Sexual Harassment": {
      "precision": 0.8571428571428571,
      "recall": 0.9090909090909091,
      "f1-score": 0.8823529411764706,
      "support": 99.0
    },
    "Slut Shaming": {
      "precision": 0.946236559139785,
      "recall": 0.8888888888888888,
      "f1-score": 0.9166666666666666,
      "support": 99.0
    }
  },
  "weighted_avg": {
    "precision": 0.8393213090688532,
    "recall": 0.8364928909952607,
    "f1-score": 0.8370210621761828,
    "support": 422.0
  },
  "micro_avg": {
    "precision": 0.8364928909952607,
    "recall": 0.8364928909952607,
    "f1-score": 0.8364928909952607,
    "support": 422
  },
  "macro_avg": {
    "precision": 0.8281772777604551,
    "recall": 0.8280010632642213,
    "f1-score": 0.8272471625800725,
    "support": 422.0
  },
  "accuracy": 0.8364928909952607,
  "inference_time_seconds": 0.3290729522705078,
  "energy_kwh": 1.9889774833778263e-05,
  "num_test_samples": 422
}