{
  "per_class": {
    "emotion": {
      "precision": 0.9100310237849017,
      "recall": 0.8747514910536779,
      "f1-score": 0.8920425747592499,
      "support": 1006.0
    },
    "hate": {
      "precision": 0.9628732849071832,
      "recall": 0.9419660481642321,
      "f1-score": 0.9523049291558571,
      "support": 2533.0
    },
    "offensive": {
      "precision": 0.9287690179806363,
      "recall": 0.9565527065527065,
      "f1-score": 0.9424561403508772,
      "support": 2808.0
    },
    "religion": {
      "precision": 0.9937709631049353,
      "recall": 1.0,
      "f1-score": 0.996875751021389,
      "support": 2074.0
    },
    "spiritual": {
      "precision": 1.0,
      "recall": 0.9982668977469671,
      "f1-score": 0.9991326973113617,
      "support": 1731.0
    }
  },
  "weighted_avg": {
    "precision": 0.960846495327696,
    "recall": 0.960795902285264,
    "f1-score": 0.9606992774358927,
    "support": 10152.0
  },
  "micro_avg": {
    "precision": 0.960795902285264,
    "recall": 0.960795902285264,
    "f1-score": 0.960795902285264,
    "support": 10152
  },
  "macro_avg": {
    "precision": 0.9590888579555312,
    "recall": 0.9543074287035168,
    "f1-score": 0.956562418519747,
    "support": 10152.0
  },
  "accuracy": 0.960795902285264,
  "inference_time_seconds": 5.313953161239624,
  "energy_kwh": 0.0002999256524525658,
  "num_test_samples": 10152
}