{
  "per_class": {
    "age": {
      "precision": 0.9818181818181818,
      "recall": 0.9799749687108886,
      "f1-score": 0.9808957093642343,
      "support": 1598.0
    },
    "ethnicity": {
      "precision": 0.9791271347248577,
      "recall": 0.9723618090452262,
      "f1-score": 0.9757327450362433,
      "support": 1592.0
    },
    "gender": {
      "precision": 0.8823529411764706,
      "recall": 0.9245283018867925,
      "f1-score": 0.902948402948403,
      "support": 1590.0
    },
    "not_cyberbullying": {
      "precision": 0.7098214285714286,
      "recall": 0.6011342155009451,
      "f1-score": 0.6509723643807575,
      "support": 1587.0
    },
    "other_cyberbullying": {
      "precision": 0.6969168121000582,
      "recall": 0.7654952076677316,
      "f1-score": 0.7295980511571255,
      "support": 1565.0
    },
    "religion": {
      "precision": 0.9551321450522434,
      "recall": 0.97125,
      "f1-score": 0.9631236442516269,
      "support": 1600.0
    }
  },
  "weighted_avg": {
    "precision": 0.8682364540139585,
    "recall": 0.8697020562316408,
    "f1-score": 0.8678596052754378,
    "support": 9532.0
  },
  "micro_avg": {
    "precision": 0.8697020562316408,
    "recall": 0.8697020562316408,
    "f1-score": 0.8697020562316408,
    "support": 9532
  },
  "macro_avg": {
    "precision": 0.8675281072405401,
    "recall": 0.8691240838019306,
    "f1-score": 0.867211819523065,
    "support": 9532.0
  },
  "accuracy": 0.8697020562316408,
  "inference_time_seconds": 7.450565338134766,
  "energy_kwh": 0.00044272878925479957,
  "num_test_samples": 9532
}