{
  "per_class": {
    "emotion": {
      "precision": 0.837108953613808,
      "recall": 0.825531914893617,
      "f1-score": 0.8312801285484734,
      "support": 940.0
    },
    "hate": {
      "precision": 0.9465553235908142,
      "recall": 0.9387163561076605,
      "f1-score": 0.9426195426195426,
      "support": 2415.0
    },
    "offensive": {
      "precision": 0.899581589958159,
      "recall": 0.9083227714406422,
      "f1-score": 0.9039310489804498,
      "support": 2367.0
    },
    "religion": {
      "precision": 0.9946262823644357,
      "recall": 1.0,
      "f1-score": 0.9973059025226549,
      "support": 2036.0
    },
    "spiritual": {
      "precision": 0.9994158878504673,
      "recall": 0.9988324576765908,
      "f1-score": 0.9991240875912408,
      "support": 1713.0
    }
  },
  "weighted_avg": {
    "precision": 0.9438477112323514,
    "recall": 0.943934114665822,
    "f1-score": 0.9438759042105803,
    "support": 9471.0
  },
  "micro_avg": {
    "precision": 0.943934114665822,
    "recall": 0.943934114665822,
    "f1-score": 0.943934114665822,
    "support": 9471
  },
  "macro_avg": {
    "precision": 0.9354576074755367,
    "recall": 0.9342807000237021,
    "f1-score": 0.9348521420524725,
    "support": 9471.0
  },
  "accuracy": 0.943934114665822,
  "inference_time_seconds": 2.3299553394317627,
  "energy_kwh": 0.00013184627295421449,
  "num_test_samples": 9471
}