{
  "per_class": {
    "age": {
      "precision": 0.9722735674676525,
      "recall": 0.9874843554443054,
      "f1-score": 0.9798199316982303,
      "support": 1598.0
    },
    "ethnicity": {
      "precision": 0.9866497139224412,
      "recall": 0.9748743718592965,
      "f1-score": 0.9807266982622432,
      "support": 1592.0
    },
    "gender": {
      "precision": 0.9066403681788298,
      "recall": 0.8672955974842768,
      "f1-score": 0.8865316618450659,
      "support": 1590.0
    },
    "not_cyberbullying": {
      "precision": 0.6918882072256305,
      "recall": 0.6395715185885318,
      "f1-score": 0.664702030124427,
      "support": 1587.0
    },
    "other_cyberbullying": {
      "precision": 0.6976065382370111,
      "recall": 0.7635782747603834,
      "f1-score": 0.7291031116534472,
      "support": 1565.0
    },
    "religion": {
      "precision": 0.9504587155963303,
      "recall": 0.97125,
      "f1-score": 0.960741885625966,
      "support": 1600.0
    }
  },
  "weighted_avg": {
    "precision": 0.8682870806697756,
    "recall": 0.8679185900125892,
    "f1-score": 0.8675797319940802,
    "support": 9532.0
  },
  "micro_avg": {
    "precision": 0.8679185900125892,
    "recall": 0.8679185900125892,
    "f1-score": 0.8679185900125892,
    "support": 9532
  },
  "macro_avg": {
    "precision": 0.8675861851046491,
    "recall": 0.8673423530227989,
    "f1-score": 0.8669375532015633,
    "support": 9532.0
  },
  "accuracy": 0.8679185900125892,
  "inference_time_seconds": 3.6624960899353027,
  "energy_kwh": 0.00023509975942524023,
  "num_test_samples": 9532
}