{
  "per_class": {
    "Cyberstalking": {
      "precision": 0.782608695652174,
      "recall": 0.6923076923076923,
      "f1-score": 0.7346938775510204,
      "support": 52.0
    },
    "Doxing": {
      "precision": 0.8529411764705882,
      "recall": 0.7837837837837838,
      "f1-score": 0.8169014084507042,
      "support": 74.0
    },
    "Revenge Porn": {
      "precision": 0.8769230769230769,
      "recall": 0.8260869565217391,
      "f1-score": 0.8507462686567164,
      "support": 69.0
    },
    "Sexual Harassment": {
      "precision": 0.8111111111111111,
      "recall": 0.9358974358974359,
      "f1-score": 0.8690476190476191,
      "support": 78.0
    },
    "Slut Shaming": {
      "precision": 0.8723404255319149,
      "recall": 0.9111111111111111,
      "f1-score": 0.8913043478260869,
      "support": 90.0
    }
  },
  "weighted_avg": {
    "precision": 0.8432459958814542,
    "recall": 0.8429752066115702,
    "f1-score": 0.8412104242021506,
    "support": 363.0
  },
  "micro_avg": {
    "precision": 0.8429752066115702,
    "recall": 0.8429752066115702,
    "f1-score": 0.8429752066115702,
    "support": 363
  },
  "macro_avg": {
    "precision": 0.839184897137773,
    "recall": 0.8298373959243526,
    "f1-score": 0.8325387043064294,
    "support": 363.0
  },
  "accuracy": 0.8429752066115702,
  "inference_time_seconds": 0.32025146484375,
  "energy_kwh": 1.1356124479858971e-05,
  "num_test_samples": 363
}