{
  "per_class": {
    "age": {
      "precision": 0.9857054070851461,
      "recall": 0.99125,
      "f1-score": 0.9884699283265815,
      "support": 1600.0
    },
    "ethnicity": {
      "precision": 0.9874371859296482,
      "recall": 0.9825,
      "f1-score": 0.9849624060150376,
      "support": 1600.0
    },
    "gender": {
      "precision": 0.9238095238095239,
      "recall": 0.9088069956277327,
      "f1-score": 0.9162468513853904,
      "support": 1601.0
    },
    "other_cyberbullying": {
      "precision": 0.8923547400611621,
      "recall": 0.9113054341036851,
      "f1-score": 0.9017305315203955,
      "support": 1601.0
    },
    "religion": {
      "precision": 0.9912005028284098,
      "recall": 0.985625,
      "f1-score": 0.9884048887496083,
      "support": 1600.0
    }
  },
  "weighted_avg": {
    "precision": 0.9560894701082349,
    "recall": 0.9558860284928767,
    "f1-score": 0.9559511805771217,
    "support": 8002.0
  },
  "micro_avg": {
    "precision": 0.9558860284928767,
    "recall": 0.9558860284928767,
    "f1-score": 0.9558860284928767,
    "support": 8002
  },
  "macro_avg": {
    "precision": 0.956101471942778,
    "recall": 0.9558974859462834,
    "f1-score": 0.9559629211994027,
    "support": 8002.0
  },
  "accuracy": 0.9558860284928767,
  "inference_time_seconds": 2.985013961791992,
  "energy_kwh": 0.00019721879465256094,
  "num_test_samples": 8002
}