{
  "per_class": {
    "Cyberstalking": {
      "precision": 0.8333333333333334,
      "recall": 0.6666666666666666,
      "f1-score": 0.7407407407407407,
      "support": 60.0
    },
    "Doxing": {
      "precision": 0.74,
      "recall": 0.8409090909090909,
      "f1-score": 0.7872340425531915,
      "support": 88.0
    },
    "Revenge Porn": {
      "precision": 0.7974683544303798,
      "recall": 0.8289473684210527,
      "f1-score": 0.8129032258064516,
      "support": 76.0
    },
    "Sexual Harassment": {
      "precision": 0.8775510204081632,
      "recall": 0.8686868686868687,
      "f1-score": 0.8730964467005076,
      "support": 99.0
    },
    "Slut Shaming": {
      "precision": 0.9175257731958762,
      "recall": 0.898989898989899,
      "f1-score": 0.9081632653061225,
      "support": 99.0
    }
  },
  "weighted_avg": {
    "precision": 0.8375360130414901,
    "recall": 0.8341232227488151,
    "f1-score": 0.8337592342158104,
    "support": 422.0
  },
  "micro_avg": {
    "precision": 0.8341232227488151,
    "recall": 0.8341232227488151,
    "f1-score": 0.8341232227488151,
    "support": 422
  },
  "macro_avg": {
    "precision": 0.8331756962735504,
    "recall": 0.8208399787347155,
    "f1-score": 0.8244275442214029,
    "support": 422.0
  },
  "accuracy": 0.8341232227488151,
  "inference_time_seconds": 0.31670117378234863,
  "energy_kwh": 1.923188431815112e-05,
  "num_test_samples": 422
}