{
  "per_class": {
    "emotion": {
      "precision": 0.8576051779935275,
      "recall": 0.790258449304175,
      "f1-score": 0.8225556130367304,
      "support": 1006.0
    },
    "hate": {
      "precision": 0.9357798165137615,
      "recall": 0.9261744966442953,
      "f1-score": 0.930952380952381,
      "support": 2533.0
    },
    "offensive": {
      "precision": 0.8863636363636364,
      "recall": 0.9166666666666666,
      "f1-score": 0.9012605042016807,
      "support": 2808.0
    },
    "religion": {
      "precision": 0.9942473633748802,
      "recall": 1.0,
      "f1-score": 0.9971153846153846,
      "support": 2074.0
    },
    "spiritual": {
      "precision": 1.0,
      "recall": 0.9982668977469671,
      "f1-score": 0.9991326973113617,
      "support": 1731.0
    }
  },
  "weighted_avg": {
    "precision": 0.9372595751417888,
    "recall": 0.9374507486209613,
    "f1-score": 0.9371403497048785,
    "support": 10152.0
  },
  "micro_avg": {
    "precision": 0.9374507486209613,
    "recall": 0.9374507486209613,
    "f1-score": 0.9374507486209613,
    "support": 10152
  },
  "macro_avg": {
    "precision": 0.9347991988491611,
    "recall": 0.9262733020724209,
    "f1-score": 0.9302033160235077,
    "support": 10152.0
  },
  "accuracy": 0.9374507486209613,
  "inference_time_seconds": 2.680548906326294,
  "energy_kwh": 0.00016315515925728968,
  "num_test_samples": 10152
}