{
  "per_class": {
    "age": {
      "precision": 0.9814471243042672,
      "recall": 0.991875,
      "f1-score": 0.9866335094808828,
      "support": 1600.0
    },
    "ethnicity": {
      "precision": 0.9949109414758269,
      "recall": 0.9775,
      "f1-score": 0.9861286254728878,
      "support": 1600.0
    },
    "gender": {
      "precision": 0.931950745301361,
      "recall": 0.8981886321049344,
      "f1-score": 0.9147582697201018,
      "support": 1601.0
    },
    "other_cyberbullying": {
      "precision": 0.8757431629013079,
      "recall": 0.920049968769519,
      "f1-score": 0.8973499847700274,
      "support": 1601.0
    },
    "religion": {
      "precision": 0.9918136020151134,
      "recall": 0.984375,
      "f1-score": 0.9880803011292346,
      "support": 1600.0
    }
  },
  "weighted_avg": {
    "precision": 0.955160286866384,
    "recall": 0.9543864033991503,
    "f1-score": 0.954578007144652,
    "support": 8002.0
  },
  "micro_avg": {
    "precision": 0.9543864033991503,
    "recall": 0.9543864033991503,
    "f1-score": 0.9543864033991503,
    "support": 8002
  },
  "macro_avg": {
    "precision": 0.9551731151995753,
    "recall": 0.9543977201748906,
    "f1-score": 0.9545901381146269,
    "support": 8002.0
  },
  "accuracy": 0.9543864033991503,
  "inference_time_seconds": 6.856119394302368,
  "energy_kwh": 0.00034262926291489374,
  "num_test_samples": 8002
}