{
  "per_class": {
    "emotion": {
      "precision": 0.8531390134529148,
      "recall": 0.8121664887940235,
      "f1-score": 0.8321487151448879,
      "support": 937.0
    },
    "hate": {
      "precision": 0.9550898203592815,
      "recall": 0.926171712982165,
      "f1-score": 0.9404085070541166,
      "support": 2411.0
    },
    "offensive": {
      "precision": 0.8840404040404041,
      "recall": 0.9255499153976311,
      "f1-score": 0.904319074188882,
      "support": 2364.0
    },
    "religion": {
      "precision": 0.9951219512195122,
      "recall": 1.0,
      "f1-score": 0.9975550122249389,
      "support": 2040.0
    },
    "spiritual": {
      "precision": 1.0,
      "recall": 0.9982476635514018,
      "f1-score": 0.9991230634317451,
      "support": 1712.0
    }
  },
  "weighted_avg": {
    "precision": 0.9440018077061421,
    "recall": 0.9436813186813187,
    "f1-score": 0.9436146933130574,
    "support": 9464.0
  },
  "micro_avg": {
    "precision": 0.9436813186813187,
    "recall": 0.9436813186813187,
    "f1-score": 0.9436813186813187,
    "support": 9464
  },
  "macro_avg": {
    "precision": 0.9374782378144225,
    "recall": 0.9324271561450443,
    "f1-score": 0.9347108744089141,
    "support": 9464.0
  },
  "accuracy": 0.9436813186813187,
  "inference_time_seconds": 15.842528581619263,
  "energy_kwh": 0.0008971053250493947,
  "num_test_samples": 9464
}