{
  "per_class": {
    "age": {
      "precision": 0.9899812147777082,
      "recall": 0.988125,
      "f1-score": 0.9890522364716922,
      "support": 1600.0
    },
    "ethnicity": {
      "precision": 0.993666877770741,
      "recall": 0.980625,
      "f1-score": 0.9871028625353885,
      "support": 1600.0
    },
    "gender": {
      "precision": 0.8996845425867508,
      "recall": 0.8906933166770769,
      "f1-score": 0.8951663527934715,
      "support": 1601.0
    },
    "other_cyberbullying": {
      "precision": 0.861965039180229,
      "recall": 0.8931917551530294,
      "f1-score": 0.8773006134969326,
      "support": 1601.0
    },
    "religion": {
      "precision": 0.988621997471555,
      "recall": 0.9775,
      "f1-score": 0.983029541169076,
      "support": 1600.0
    }
  },
  "weighted_avg": {
    "precision": 0.9467674486929445,
    "recall": 0.9460134966258436,
    "f1-score": 0.9463153008388886,
    "support": 8002.0
  },
  "micro_avg": {
    "precision": 0.9460134966258436,
    "recall": 0.9460134966258436,
    "f1-score": 0.9460134966258436,
    "support": 8002
  },
  "macro_avg": {
    "precision": 0.9467839343573967,
    "recall": 0.9460270143660212,
    "f1-score": 0.9463303212933122,
    "support": 8002.0
  },
  "accuracy": 0.9460134966258436,
  "inference_time_seconds": 13.193069696426392,
  "energy_kwh": 0.0007762808829759289,
  "num_test_samples": 8002
}