{
  "per_class": {
    "emotion": {
      "precision": 0.8344086021505376,
      "recall": 0.8264110756123536,
      "f1-score": 0.8303905831995719,
      "support": 939.0
    },
    "hate": {
      "precision": 0.9390946502057613,
      "recall": 0.9453189726594863,
      "f1-score": 0.9421965317919075,
      "support": 2414.0
    },
    "offensive": {
      "precision": 0.9057971014492754,
      "recall": 0.9000423549343498,
      "f1-score": 0.9029105587422988,
      "support": 2361.0
    },
    "religion": {
      "precision": 0.994140625,
      "recall": 0.9995090819833088,
      "f1-score": 0.9968176254589963,
      "support": 2037.0
    },
    "spiritual": {
      "precision": 1.0,
      "recall": 0.9982486865148862,
      "f1-score": 0.9991235758106923,
      "support": 1713.0
    }
  },
  "weighted_avg": {
    "precision": 0.9432729895036773,
    "recall": 0.9434699915469146,
    "f1-score": 0.9433629758013864,
    "support": 9464.0
  },
  "micro_avg": {
    "precision": 0.9434699915469146,
    "recall": 0.9434699915469146,
    "f1-score": 0.9434699915469146,
    "support": 9464
  },
  "macro_avg": {
    "precision": 0.934688195761115,
    "recall": 0.9339060343408769,
    "f1-score": 0.9342877750006933,
    "support": 9464.0
  },
  "accuracy": 0.9434699915469146,
  "inference_time_seconds": 4.026977300643921,
  "energy_kwh": 0.00021993210854565637,
  "num_test_samples": 9464
}