{
  "per_class": {
    "emotion": {
      "precision": 0.9159751037344398,
      "recall": 0.8777335984095428,
      "f1-score": 0.8964467005076142,
      "support": 1006.0
    },
    "hate": {
      "precision": 0.9515316013958899,
      "recall": 0.9688116857481247,
      "f1-score": 0.960093896713615,
      "support": 2533.0
    },
    "offensive": {
      "precision": 0.9596716630977873,
      "recall": 0.9576210826210826,
      "f1-score": 0.9586452762923351,
      "support": 2808.0
    },
    "religion": {
      "precision": 0.9975949975949976,
      "recall": 1.0,
      "f1-score": 0.9987960510474356,
      "support": 2074.0
    },
    "spiritual": {
      "precision": 1.0,
      "recall": 0.9982668977469671,
      "f1-score": 0.9991326973113617,
      "support": 1731.0
    }
  },
  "weighted_avg": {
    "precision": 0.967934451899453,
    "recall": 0.9680851063829787,
    "f1-score": 0.9679492578638172,
    "support": 10152.0
  },
  "micro_avg": {
    "precision": 0.9680851063829787,
    "recall": 0.9680851063829787,
    "f1-score": 0.9680851063829787,
    "support": 10152
  },
  "macro_avg": {
    "precision": 0.9649546731646229,
    "recall": 0.9604866529051435,
    "f1-score": 0.9626229243744723,
    "support": 10152.0
  },
  "accuracy": 0.9680851063829787,
  "inference_time_seconds": 4.973881006240845,
  "energy_kwh": 0.00031793070041821254,
  "num_test_samples": 10152
}