{
  "per_class": {
    "Cyberstalking": {
      "precision": 0.746031746031746,
      "recall": 0.7833333333333333,
      "f1-score": 0.7642276422764228,
      "support": 60.0
    },
    "Doxing": {
      "precision": 0.8192771084337349,
      "recall": 0.7727272727272727,
      "f1-score": 0.7953216374269005,
      "support": 88.0
    },
    "Revenge Porn": {
      "precision": 0.8,
      "recall": 0.7894736842105263,
      "f1-score": 0.7947019867549668,
      "support": 76.0
    },
    "Sexual Harassment": {
      "precision": 0.8301886792452831,
      "recall": 0.8888888888888888,
      "f1-score": 0.8585365853658536,
      "support": 99.0
    },
    "Slut Shaming": {
      "precision": 0.9473684210526315,
      "recall": 0.9090909090909091,
      "f1-score": 0.9278350515463918,
      "support": 99.0
    }
  },
  "weighted_avg": {
    "precision": 0.8380010503165094,
    "recall": 0.8364928909952607,
    "f1-score": 0.8367064115588683,
    "support": 422.0
  },
  "micro_avg": {
    "precision": 0.8364928909952607,
    "recall": 0.8364928909952607,
    "f1-score": 0.8364928909952607,
    "support": 422
  },
  "macro_avg": {
    "precision": 0.8285731909526792,
    "recall": 0.8287028176501859,
    "f1-score": 0.8281245806741071,
    "support": 422.0
  },
  "accuracy": 0.8364928909952607,
  "inference_time_seconds": 0.3209669589996338,
  "energy_kwh": 3.853689943543923e-05,
  "num_test_samples": 422
}