{
  "per_class": {
    "emotion": {
      "precision": 0.8665879574970484,
      "recall": 0.7800212539851222,
      "f1-score": 0.8210290827740492,
      "support": 941.0
    },
    "hate": {
      "precision": 0.9502127659574469,
      "recall": 0.9265560165975104,
      "f1-score": 0.9382352941176471,
      "support": 2410.0
    },
    "offensive": {
      "precision": 0.8706586826347306,
      "recall": 0.9233700254022015,
      "f1-score": 0.8962399835627697,
      "support": 2362.0
    },
    "religion": {
      "precision": 0.9936647173489279,
      "recall": 1.0,
      "f1-score": 0.9968222928379369,
      "support": 2039.0
    },
    "spiritual": {
      "precision": 1.0,
      "recall": 0.9988331388564761,
      "f1-score": 0.9994162288382954,
      "support": 1714.0
    }
  },
  "weighted_avg": {
    "precision": 0.9404236426177759,
    "recall": 0.9401014155926474,
    "f1-score": 0.9398029091711984,
    "support": 9466.0
  },
  "micro_avg": {
    "precision": 0.9401014155926474,
    "recall": 0.9401014155926474,
    "f1-score": 0.9401014155926474,
    "support": 9466
  },
  "macro_avg": {
    "precision": 0.9362248246876307,
    "recall": 0.9257560869682621,
    "f1-score": 0.9303485764261396,
    "support": 9466.0
  },
  "accuracy": 0.9401014155926474,
  "inference_time_seconds": 6.660559415817261,
  "energy_kwh": 0.00038112745332962437,
  "num_test_samples": 9466
}