{
  "per_class": {
    "emotion": {
      "precision": 0.8457330415754923,
      "recall": 0.8249733191035219,
      "f1-score": 0.8352242031334414,
      "support": 937.0
    },
    "hate": {
      "precision": 0.9454926624737946,
      "recall": 0.9356846473029046,
      "f1-score": 0.940563086548488,
      "support": 2410.0
    },
    "offensive": {
      "precision": 0.8981210855949896,
      "recall": 0.9122137404580153,
      "f1-score": 0.9051125604881127,
      "support": 2358.0
    },
    "religion": {
      "precision": 0.9931640625,
      "recall": 1.0,
      "f1-score": 0.9965703086722195,
      "support": 2034.0
    },
    "spiritual": {
      "precision": 1.0,
      "recall": 0.9982497082847142,
      "f1-score": 0.9991240875912408,
      "support": 1714.0
    }
  },
  "weighted_avg": {
    "precision": 0.9439283189967278,
    "recall": 0.9440389294403893,
    "f1-score": 0.9439479772050716,
    "support": 9453.0
  },
  "micro_avg": {
    "precision": 0.9440389294403893,
    "recall": 0.9440389294403893,
    "f1-score": 0.9440389294403893,
    "support": 9453
  },
  "macro_avg": {
    "precision": 0.9365021704288553,
    "recall": 0.9342242830298313,
    "f1-score": 0.9353188492867005,
    "support": 9453.0
  },
  "accuracy": 0.9440389294403893,
  "inference_time_seconds": 6.7397966384887695,
  "energy_kwh": 0.0003825528987593787,
  "num_test_samples": 9453
}