{
  "per_class": {
    "Cyberstalking": {
      "precision": 0.8333333333333334,
      "recall": 0.7017543859649122,
      "f1-score": 0.7619047619047619,
      "support": 57.0
    },
    "Doxing": {
      "precision": 0.8356164383561644,
      "recall": 0.7625,
      "f1-score": 0.7973856209150327,
      "support": 80.0
    },
    "Revenge Porn": {
      "precision": 0.7469879518072289,
      "recall": 0.8732394366197183,
      "f1-score": 0.8051948051948052,
      "support": 71.0
    },
    "Sexual Harassment": {
      "precision": 0.8421052631578947,
      "recall": 0.7804878048780488,
      "f1-score": 0.810126582278481,
      "support": 82.0
    },
    "Slut Shaming": {
      "precision": 0.8484848484848485,
      "recall": 0.9438202247191011,
      "f1-score": 0.8936170212765957,
      "support": 89.0
    }
  },
  "weighted_avg": {
    "precision": 0.8230956272847105,
    "recall": 0.820580474934037,
    "f1-score": 0.818866878393292,
    "support": 379.0
  },
  "micro_avg": {
    "precision": 0.820580474934037,
    "recall": 0.820580474934037,
    "f1-score": 0.820580474934037,
    "support": 379
  },
  "macro_avg": {
    "precision": 0.8213055670278939,
    "recall": 0.812360370436356,
    "f1-score": 0.8136457583139352,
    "support": 379.0
  },
  "accuracy": 0.820580474934037,
  "inference_time_seconds": 0.2324206829071045,
  "energy_kwh": 1.238291339349037e-05,
  "num_test_samples": 379
}