{
  "per_class": {
    "age": {
      "precision": 0.9728395061728395,
      "recall": 0.986232790988736,
      "f1-score": 0.9794903666873834,
      "support": 1598.0
    },
    "ethnicity": {
      "precision": 0.9942492012779552,
      "recall": 0.9773869346733668,
      "f1-score": 0.9857459613557175,
      "support": 1592.0
    },
    "gender": {
      "precision": 0.8909774436090225,
      "recall": 0.8943396226415095,
      "f1-score": 0.8926553672316384,
      "support": 1590.0
    },
    "not_cyberbullying": {
      "precision": 0.7630744849445324,
      "recall": 0.6068052930056711,
      "f1-score": 0.676026676026676,
      "support": 1587.0
    },
    "other_cyberbullying": {
      "precision": 0.6958904109589041,
      "recall": 0.8115015974440895,
      "f1-score": 0.7492625368731564,
      "support": 1565.0
    },
    "religion": {
      "precision": 0.9447115384615384,
      "recall": 0.9825,
      "f1-score": 0.9632352941176471,
      "support": 1600.0
    }
  },
  "weighted_avg": {
    "precision": 0.8776439946425899,
    "recall": 0.8769408308854385,
    "f1-score": 0.8749980996634606,
    "support": 9532.0
  },
  "micro_avg": {
    "precision": 0.8769408308854385,
    "recall": 0.8769408308854385,
    "f1-score": 0.8769408308854385,
    "support": 9532
  },
  "macro_avg": {
    "precision": 0.8769570975707986,
    "recall": 0.8764610397922289,
    "f1-score": 0.8744027003820364,
    "support": 9532.0
  },
  "accuracy": 0.8769408308854385,
  "inference_time_seconds": 2.2468209266662598,
  "energy_kwh": 0.00011616023672602383,
  "num_test_samples": 9532
}