{
  "per_class": {
    "Cyberstalking": {
      "precision": 0.765625,
      "recall": 0.8166666666666667,
      "f1-score": 0.7903225806451613,
      "support": 60.0
    },
    "Doxing": {
      "precision": 0.8607594936708861,
      "recall": 0.7727272727272727,
      "f1-score": 0.8143712574850299,
      "support": 88.0
    },
    "Revenge Porn": {
      "precision": 0.8,
      "recall": 0.8421052631578947,
      "f1-score": 0.8205128205128205,
      "support": 76.0
    },
    "Sexual Harassment": {
      "precision": 0.839622641509434,
      "recall": 0.898989898989899,
      "f1-score": 0.8682926829268293,
      "support": 99.0
    },
    "Slut Shaming": {
      "precision": 0.956989247311828,
      "recall": 0.898989898989899,
      "f1-score": 0.9270833333333334,
      "support": 99.0
    }
  },
  "weighted_avg": {
    "precision": 0.8539073754415709,
    "recall": 0.8507109004739336,
    "f1-score": 0.8511498233794378,
    "support": 422.0
  },
  "micro_avg": {
    "precision": 0.8507109004739336,
    "recall": 0.8507109004739336,
    "f1-score": 0.8507109004739336,
    "support": 422
  },
  "macro_avg": {
    "precision": 0.8445992764984297,
    "recall": 0.8458958001063264,
    "f1-score": 0.8441165349806348,
    "support": 422.0
  },
  "accuracy": 0.8507109004739336,
  "inference_time_seconds": 0.22565937042236328,
  "energy_kwh": 1.2341907443947803e-05,
  "num_test_samples": 422
}