{
  "per_class": {
    "emotion": {
      "precision": 0.8308751229105211,
      "recall": 0.8399602385685885,
      "f1-score": 0.8353929807217004,
      "support": 1006.0
    },
    "hate": {
      "precision": 0.9316646801748113,
      "recall": 0.9257797078562969,
      "f1-score": 0.9287128712871288,
      "support": 2533.0
    },
    "offensive": {
      "precision": 0.9212121212121213,
      "recall": 0.9202279202279202,
      "f1-score": 0.9207197577053269,
      "support": 2808.0
    },
    "religion": {
      "precision": 0.9952015355086372,
      "recall": 1.0,
      "f1-score": 0.9975949975949976,
      "support": 2074.0
    },
    "spiritual": {
      "precision": 1.0,
      "recall": 0.998844598497978,
      "f1-score": 0.999421965317919,
      "support": 1731.0
    }
  },
  "weighted_avg": {
    "precision": 0.9434179107111239,
    "recall": 0.943360914105595,
    "f1-score": 0.9433833301999831,
    "support": 10152.0
  },
  "micro_avg": {
    "precision": 0.943360914105595,
    "recall": 0.943360914105595,
    "f1-score": 0.943360914105595,
    "support": 10152
  },
  "macro_avg": {
    "precision": 0.9357906919612182,
    "recall": 0.9369624930301568,
    "f1-score": 0.9363685145254145,
    "support": 10152.0
  },
  "accuracy": 0.943360914105595,
  "inference_time_seconds": 2.300881862640381,
  "energy_kwh": 0.0001351015429190985,
  "num_test_samples": 10152
}